bltest/__init__.py
bltest/extra_asserts.py
bltest/random_data.py
bltest-1.1.0.dist-info/METADATA
bltest-1.1.0.dist-info/RECORD
bltest-1.1.0.dist-info/WHEEL
bltest-1.1.0.dist-info/top_level.txt
