Metadata-Version: 2.1
Name: bltest
Version: 1.1.0
Summary: BodyLabs unittest extensions
Home-page: https://github.com/bodylabs/___
Author: Body Labs
Author-email: aw@bodylabs.com
License: MIT
Platform: UNKNOWN
Classifier: Development Status :: 3 - Alpha
Classifier: Intended Audience :: Developers
Classifier: License :: OSI Approved :: BSD License
Classifier: Operating System :: OS Independent
Classifier: Programming Language :: Python
Requires-Dist: baiji (>=2.5.3)
Requires-Dist: numpy (>=1.10.1)
